icpmsflow/__init__.py
icpmsflow/_plotbounds.py
icpmsflow/cached_decorators.py
icpmsflow/core.py
icpmsflow/exampledata.py
icpmsflow/interface.py
icpmsflow/plotbounds.py
icpmsflow/plotbounds_old.py
icpmsflow/utilities.py
tests/__init__.py
tests/test_import.py
icpmsflow-0.1.0.dist-info/LICENSE
icpmsflow-0.1.0.dist-info/METADATA
icpmsflow-0.1.0.dist-info/WHEEL
icpmsflow-0.1.0.dist-info/top_level.txt
icpmsflow-0.1.0.dist-info/RECORD
