Metadata-Version: 2.1
Name: icpmsflow
Version: 0.1.0
Summary: Package to work with icpms data
Home-page: https://github.com/wpk-nist-gov/icpmsflow
Author: William P. Krekelberg
Author-email: wpk@nist.gov
License: NIST license
Keywords: icpmsflow
Platform: UNKNOWN
Classifier: Development Status :: 2 - Pre-Alpha
Classifier: License :: Public Domain
Classifier: Operating System :: OS Independent
Classifier: Intended Audience :: Science/Research
Classifier: Programming Language :: Python
Classifier: Programming Language :: Python :: 3
Classifier: Programming Language :: Python :: 3.6
Classifier: Programming Language :: Python :: 3.7
Classifier: Programming Language :: Python :: 3.8
Classifier: Topic :: Scientific/Engineering
Requires-Python: >=3.6
Requires-Dist: setuptools (>=38.4)
Requires-Dist: numpy
Requires-Dist: pandas
Requires-Dist: scipy
Provides-Extra: all
Requires-Dist: openpyxl ; extra == 'all'
Requires-Dist: holoviews ; extra == 'all'
Requires-Dist: bokeh ; extra == 'all'
Requires-Dist: matplotlib ; extra == 'all'
Requires-Dist: jupyter ; extra == 'all'
